{
  "name": "迷宫地图",
  "description": "复杂的迷宫布局，考验策略和走位",
  "original_width": 800,
  "original_height": 600,
  "aspect_ratio": 1.7777777777777777,
  "width": 1280,
  "height": 720,
  "grid_size": 50,
  "wall_grid_data": [
    {
      "grid_x": 2,
      "grid_y": 2,
      "type": 1
    },
    {
      "grid_x": 3,
      "grid_y": 2,
      "type": 1
    },
    {
      "grid_x": 4,
      "grid_y": 2,
      "type": 1
    },
    {
      "grid_x": 5,
      "grid_y": 2,
      "type": 1
    },
    {
      "grid_x": 11,
      "grid_y": 2,
      "type": 1
    },
    {
      "grid_x": 12,
      "grid_y": 2,
      "type": 1
    },
    {
      "grid_x": 13,
      "grid_y": 2,
      "type": 1
    },
    {
      "grid_x": 14,
      "grid_y": 2,
      "type": 1
    },
    {
      "grid_x": 2,
      "grid_y": 4,
      "type": 2
    },
    {
      "grid_x": 3,
      "grid_y": 4,
      "type": 2
    },
    {
      "grid_x": 4,
      "grid_y": 4,
      "type": 2
    },
    {
      "grid_x": 12,
      "grid_y": 4,
      "type": 2
    },
    {
      "grid_x": 13,
      "grid_y": 4,
      "type": 2
    },
    {
      "grid_x": 14,
      "grid_y": 4,
      "type": 2
    },
    {
      "grid_x": 6,
      "grid_y": 5,
      "type": 1
    },
    {
      "grid_x": 7,
      "grid_y": 5,
      "type": 1
    },
    {
      "grid_x": 8,
      "grid_y": 5,
      "type": 1
    },
    {
      "grid_x": 9,
      "grid_y": 5,
      "type": 1
    },
    {
      "grid_x": 10,
      "grid_y": 5,
      "type": 1
    },
    {
      "grid_x": 6,
      "grid_y": 7,
      "type": 1
    },
    {
      "grid_x": 7,
      "grid_y": 7,
      "type": 1
    },
    {
      "grid_x": 8,
      "grid_y": 7,
      "type": 1
    },
    {
      "grid_x": 9,
      "grid_y": 7,
      "type": 1
    },
    {
      "grid_x": 10,
      "grid_y": 7,
      "type": 1
    },
    {
      "grid_x": 2,
      "grid_y": 9,
      "type": 1
    },
    {
      "grid_x": 3,
      "grid_y": 9,
      "type": 1
    },
    {
      "grid_x": 4,
      "grid_y": 9,
      "type": 1
    },
    {
      "grid_x": 12,
      "grid_y": 9,
      "type": 1
    },
    {
      "grid_x": 13,
      "grid_y": 9,
      "type": 1
    },
    {
      "grid_x": 14,
      "grid_y": 9,
      "type": 1
    },
    {
      "grid_x": 7,
      "grid_y": 10,
      "type": 5
    },
    {
      "grid_x": 6,
      "grid_y": 10,
      "type": 2
    },
    {
      "grid_x": 8,
      "grid_y": 10,
      "type": 2
    },
    {
      "grid_x": 7,
      "grid_y": 9,
      "type": 2
    },
    {
      "grid_x": 6,
      "grid_y": 9,
      "type": 2
    },
    {
      "grid_x": 8,
      "grid_y": 9,
      "type": 2
    }
  ],
  "player_spawns_grid": [
    [
      5,
      11
    ],
    [
      9,
      11
    ]
  ],
  "enemy_spawns_grid": [
    [
      3,
      1
    ],
    [
      8,
      1
    ],
    [
      13,
      1
    ]
  ],
  "walls": [
    {
      "x": 100,
      "y": 100,
      "type": 1
    },
    {
      "x": 150,
      "y": 100,
      "type": 1
    },
    {
      "x": 200,
      "y": 100,
      "type": 1
    },
    {
      "x": 250,
      "y": 100,
      "type": 1
    },
    {
      "x": 550,
      "y": 100,
      "type": 1
    },
    {
      "x": 600,
      "y": 100,
      "type": 1
    },
    {
      "x": 650,
      "y": 100,
      "type": 1
    },
    {
      "x": 700,
      "y": 100,
      "type": 1
    },
    {
      "x": 100,
      "y": 200,
      "type": 2
    },
    {
      "x": 150,
      "y": 200,
      "type": 2
    },
    {
      "x": 200,
      "y": 200,
      "type": 2
    },
    {
      "x": 600,
      "y": 200,
      "type": 2
    },
    {
      "x": 650,
      "y": 200,
      "type": 2
    },
    {
      "x": 700,
      "y": 200,
      "type": 2
    },
    {
      "x": 300,
      "y": 250,
      "type": 1
    },
    {
      "x": 350,
      "y": 250,
      "type": 1
    },
    {
      "x": 400,
      "y": 250,
      "type": 1
    },
    {
      "x": 450,
      "y": 250,
      "type": 1
    },
    {
      "x": 500,
      "y": 250,
      "type": 1
    },
    {
      "x": 300,
      "y": 350,
      "type": 1
    },
    {
      "x": 350,
      "y": 350,
      "type": 1
    },
    {
      "x": 400,
      "y": 350,
      "type": 1
    },
    {
      "x": 450,
      "y": 350,
      "type": 1
    },
    {
      "x": 500,
      "y": 350,
      "type": 1
    },
    {
      "x": 100,
      "y": 450,
      "type": 1
    },
    {
      "x": 150,
      "y": 450,
      "type": 1
    },
    {
      "x": 200,
      "y": 450,
      "type": 1
    },
    {
      "x": 600,
      "y": 450,
      "type": 1
    },
    {
      "x": 650,
      "y": 450,
      "type": 1
    },
    {
      "x": 700,
      "y": 450,
      "type": 1
    },
    {
      "x": 350,
      "y": 500,
      "type": 5
    },
    {
      "x": 300,
      "y": 500,
      "type": 2
    },
    {
      "x": 400,
      "y": 500,
      "type": 2
    },
    {
      "x": 350,
      "y": 450,
      "type": 2
    },
    {
      "x": 300,
      "y": 450,
      "type": 2
    },
    {
      "x": 400,
      "y": 450,
      "type": 2
    }
  ],
  "player_spawns": [
    [
      250,
      550
    ],
    [
      450,
      550
    ]
  ],
  "enemy_spawns": [
    [
      150,
      50
    ],
    [
      400,
      50
    ],
    [
      650,
      50
    ]
  ]
}